syelink/__init__.py
syelink/cli.py
syelink/extract.py
syelink/models.py
syelink/parser.py
syelink/plotting/__init__.py
syelink/plotting/calibration.py
syelink/plotting/style.py
syelink/plotting/validation.py
syelink-1.0.0.dist-info/METADATA
syelink-1.0.0.dist-info/WHEEL
syelink-1.0.0.dist-info/entry_points.txt
syelink-1.0.0.dist-info/RECORD
