Metadata-Version: 2.4
Name: syelink
Version: 1.0.0
Summary: Parse and analyze EyeLink eye tracker data from ASC files
Project-URL: Homepage, https://github.com/mh-salari/syelink
Project-URL: Repository, https://github.com/mh-salari/syelink
Author: mh-salari
License: MIT
Keywords: asc,calibration,eye-tracker,eye-tracking,eyelink,validation
Classifier: Development Status :: 3 - Alpha
Classifier: Intended Audience :: Science/Research
Classifier: License :: OSI Approved :: MIT License
Classifier: Programming Language :: Python :: 3
Classifier: Programming Language :: Python :: 3.11
Classifier: Programming Language :: Python :: 3.12
Classifier: Programming Language :: Python :: 3.13
Classifier: Topic :: Scientific/Engineering
Requires-Python: >=3.11
Requires-Dist: adjusttext>=1.3.0
Requires-Dist: matplotlib>=3.10.7
Requires-Dist: numpy>=2.3.0
Requires-Dist: pillow>=12.0.0
Provides-Extra: dev
Requires-Dist: pytest; extra == 'dev'
Requires-Dist: ruff; extra == 'dev'
